odoo/addons/pos_restaurant_user_restriction/README.rst
odoo/addons/pos_restaurant_user_restriction/__init__.py
odoo/addons/pos_restaurant_user_restriction/__manifest__.py
odoo/addons/pos_restaurant_user_restriction/i18n/it.po
odoo/addons/pos_restaurant_user_restriction/i18n/pos_restaurant_user_restriction.pot
odoo/addons/pos_restaurant_user_restriction/readme/CONTRIBUTORS.rst
odoo/addons/pos_restaurant_user_restriction/readme/DESCRIPTION.rst
odoo/addons/pos_restaurant_user_restriction/security/ir.model.access.csv
odoo/addons/pos_restaurant_user_restriction/static/description/icon.png
odoo/addons/pos_restaurant_user_restriction/static/description/index.html
odoo12_addon_pos_restaurant_user_restriction-12.0.1.0.0.99.dev4.dist-info/METADATA
odoo12_addon_pos_restaurant_user_restriction-12.0.1.0.0.99.dev4.dist-info/WHEEL
odoo12_addon_pos_restaurant_user_restriction-12.0.1.0.0.99.dev4.dist-info/top_level.txt
odoo12_addon_pos_restaurant_user_restriction-12.0.1.0.0.99.dev4.dist-info/RECORD
